README.rst
hypo.py
setup.py
hypo.egg-info/PKG-INFO
hypo.egg-info/SOURCES.txt
hypo.egg-info/dependency_links.txt
hypo.egg-info/entry_points.txt
hypo.egg-info/requires.txt
hypo.egg-info/top_level.txt