Metadata-Version: 1.1
Name: hypo
Version: 0.1.0
Summary: Build small applications from Hy source files
Home-page: https://github.com/koji-kojiro/hylang-hypo
Author: koji-kojiro
Author-email: kojiro0531@gmail.com
License: MIT
Platform: UNKNOWN
Classifier: Programming Language :: Python
Classifier: Programming Language :: Python :: 2
Classifier: Programming Language :: Python :: 3
Classifier: Natural Language :: English
Classifier: License :: OSI Approved :: MIT License
Classifier: Intended Audience :: Developers
Classifier: Topic :: Software Development
Classifier: Environment :: Console
Classifier: Development Status :: 4 - Beta
